odoo10_addon_product_analytic_pos-10.0.1.0.0-py2.7-nspkg.pth
odoo/addons/product_analytic_pos/README.rst
odoo/addons/product_analytic_pos/__init__.py
odoo/addons/product_analytic_pos/__manifest__.py
odoo/addons/product_analytic_pos/models/__init__.py
odoo/addons/product_analytic_pos/models/pos_order.py
odoo10_addon_product_analytic_pos-10.0.1.0.0.dist-info/DESCRIPTION.rst
odoo10_addon_product_analytic_pos-10.0.1.0.0.dist-info/METADATA
odoo10_addon_product_analytic_pos-10.0.1.0.0.dist-info/RECORD
odoo10_addon_product_analytic_pos-10.0.1.0.0.dist-info/WHEEL
odoo10_addon_product_analytic_pos-10.0.1.0.0.dist-info/metadata.json
odoo10_addon_product_analytic_pos-10.0.1.0.0.dist-info/namespace_packages.txt
odoo10_addon_product_analytic_pos-10.0.1.0.0.dist-info/top_level.txt
